{
    "CABINET": {
        "god": {
            "METADATA": {
                "GRAVITY": 3,
                "INGEST": {
                    "FIRST": 1782309297,
                    "LAST": 1782311375
                },
                "EVENT": {
                    "FIRST": [],
                    "LAST": []
                },
                "LAST_USAGE": {
                    "1739217638": [
                        "felt-sense",
                        "felt-sense"
                    ]
                }
            },
            "SHELF": {
                "universe": {
                    "METADATA": {
                        "GRAVITY": 1,
                        "INGEST": {
                            "FIRST": 1782309297,
                            "LAST": 1782309297
                        },
                        "EVENT": {
                            "FIRST": [],
                            "LAST": []
                        },
                        "LAST_USAGE": {
                            "1739217616": [
                                "alias"
                            ]
                        }
                    },
                    "BIN": {
                        "alias": {
                            "METADATA": {
                                "GRAVITY": 1,
                                "INGEST": {
                                    "FIRST": 1782309297,
                                    "LAST": 1782309297
                                },
                                "EVENT": {
                                    "FIRST": [],
                                    "LAST": []
                                }
                            },
                            "INSTANCES": {
                                "1739217616": {
                                    "jack-nim": [
                                        "crate.6327A4D175A2DCB0"
                                    ]
                                }
                            }
                        }
                    }
                },
                "felt-sense": {
                    "METADATA": {
                        "GRAVITY": 2,
                        "INGEST": {
                            "FIRST": 1782311375,
                            "LAST": 1782311375
                        },
                        "EVENT": {
                            "FIRST": [],
                            "LAST": []
                        },
                        "LAST_USAGE": {
                            "1739217638": [
                                "wires",
                                "voice"
                            ]
                        }
                    },
                    "BIN": {
                        "wires": {
                            "METADATA": {
                                "GRAVITY": 1,
                                "INGEST": {
                                    "FIRST": 1782311375,
                                    "LAST": 1782311375
                                },
                                "EVENT": {
                                    "FIRST": [],
                                    "LAST": []
                                }
                            },
                            "INSTANCES": {
                                "1739217638": {
                                    "jack-nim": [
                                        "crate.F0BA3CEFB9480629"
                                    ]
                                }
                            }
                        },
                        "voice": {
                            "METADATA": {
                                "GRAVITY": 1,
                                "INGEST": {
                                    "FIRST": 1782311375,
                                    "LAST": 1782311375
                                },
                                "EVENT": {
                                    "FIRST": [],
                                    "LAST": []
                                }
                            },
                            "INSTANCES": {
                                "1739217638": {
                                    "jack-nim": [
                                        "crate.F0BA3CEFB9480629"
                                    ]
                                }
                            }
                        }
                    }
                }
            }
        }
    }
}