{
    "CABINET": {
        "goddess": {
            "METADATA": {
                "GRAVITY": 4,
                "INGEST": {
                    "FIRST": 1782306191,
                    "LAST": 1782306353
                },
                "EVENT": {
                    "FIRST": [],
                    "LAST": []
                },
                "LAST_USAGE": {
                    "1739217602": [
                        "misery",
                        "misery",
                        "misery",
                        "dark"
                    ]
                }
            },
            "SHELF": {
                "misery": {
                    "METADATA": {
                        "GRAVITY": 3,
                        "INGEST": {
                            "FIRST": 1782306191,
                            "LAST": 1782306191
                        },
                        "EVENT": {
                            "FIRST": [],
                            "LAST": []
                        },
                        "LAST_USAGE": {
                            "1739217602": [
                                "misery",
                                "grief",
                                "suffering"
                            ]
                        }
                    },
                    "BIN": {
                        "misery": {
                            "METADATA": {
                                "GRAVITY": 1,
                                "INGEST": {
                                    "FIRST": 1782306191,
                                    "LAST": 1782306191
                                },
                                "EVENT": {
                                    "FIRST": [],
                                    "LAST": []
                                }
                            },
                            "INSTANCES": {
                                "1739217602": {
                                    "jack-nim": [
                                        "crate.4C8CFD18527865A7"
                                    ]
                                }
                            }
                        },
                        "grief": {
                            "METADATA": {
                                "GRAVITY": 1,
                                "INGEST": {
                                    "FIRST": 1782306191,
                                    "LAST": 1782306191
                                },
                                "EVENT": {
                                    "FIRST": [],
                                    "LAST": []
                                }
                            },
                            "INSTANCES": {
                                "1739217602": {
                                    "jack-nim": [
                                        "crate.4C8CFD18527865A7"
                                    ]
                                }
                            }
                        },
                        "suffering": {
                            "METADATA": {
                                "GRAVITY": 1,
                                "INGEST": {
                                    "FIRST": 1782306191,
                                    "LAST": 1782306191
                                },
                                "EVENT": {
                                    "FIRST": [],
                                    "LAST": []
                                }
                            },
                            "INSTANCES": {
                                "1739217602": {
                                    "jack-nim": [
                                        "crate.4C8CFD18527865A7"
                                    ]
                                }
                            }
                        }
                    }
                },
                "dark": {
                    "METADATA": {
                        "GRAVITY": 1,
                        "INGEST": {
                            "FIRST": 1782306353,
                            "LAST": 1782306353
                        },
                        "EVENT": {
                            "FIRST": [],
                            "LAST": []
                        },
                        "LAST_USAGE": {
                            "1739217602": [
                                "misery"
                            ]
                        }
                    },
                    "BIN": {
                        "misery": {
                            "METADATA": {
                                "GRAVITY": 1,
                                "INGEST": {
                                    "FIRST": 1782306353,
                                    "LAST": 1782306353
                                },
                                "EVENT": {
                                    "FIRST": [],
                                    "LAST": []
                                }
                            },
                            "INSTANCES": {
                                "1739217602": {
                                    "jack-nim": [
                                        "crate.92D4B71D54DECC3D"
                                    ]
                                }
                            }
                        }
                    }
                }
            }
        }
    }
}